{
  "type": "stock",
  "ticker": "000660.KS",
  "name": "SK하이닉스",
  "market": "KR",
  "held": true,
  "date": "2026-06-17",
  "price": 2521000,
  "verdict": "HOLD",
  "verdict_label": "보유 지속 + 분할 익절",
  "rr": null,
  "is_leader": true,
  "rs_3m": 158.9,
  "rs_6m": 337.8,
  "rsi": 59.2,
  "divergence": "none",
  "wave": "상승 후반 (3파말~5파 진입)",
  "credit_short": "공매도 거래대금 시장 1위(5,625억, 6/8) — 변동성 확대 요인. 신용잔고율 N/A",
  "chart": "charts/000660.KS_20260617.png",
  "fundamentals": {
    "market_cap": "1,790조",
    "rev_ttm": "132조 (YoY +198%)",
    "op_margin": 71.5,
    "fwd_pe": 6.14,
    "target": 2690121
  },
  "position": {
    "entry": 1970000,
    "stop": 1911000,
    "trail": "종가 MA20(2,149,652) 또는 6/8 스윙저점 1,911,000 이탈 시 청산"
  },
  "summary": "주도주 + forward PE 6배 + 정배열 → 보유 지속이 정답. 단 거래량 약화·컨센 목표 근접·마진 정점·삼성 HBM4 변수로 추가 매수는 금지, 7월 실적 전 1/3 익절로 이익 확정 후 잔여는 트레일링 스탑.",
  "report_md": "## 결론: 보유 지속 + 분할 익절\n\n평단 1,970,000원 / 현재가 2,521,000원 (**+28.0%**). 신규 진입 자리는 아니지만 매도를 서두를 종목도 아닙니다.\n\n## 손익비 (보유자 관점)\n\n- 컨센서스 목표 2,690,000원까지 **+6.7%**밖에 남지 않음 → 신규 진입 손익비는 미달.\n- 그러나 평단 대비 **+28% 쿠션** 확보. 보유자는 트레일링 스탑으로 추세를 끝까지 끌고 가되 일부 익절 병행.\n\n## 주도주 여부 — YES\n\n- 상대강도 3M: 종목 **+158.9%** vs KOSPI +59.7%\n- 상대강도 6M: 종목 **+337.8%** vs KOSPI +113.3%\n- 당일 52주 신고가. 시장을 끌고 가는 명백한 1등주.\n\n## 가격 / 거래량\n\nMA20 위(+17.3%) · MA60 위(+63.7%) 정배열 우상향. 다만 **신고가인데 거래량 0.84x** — 돌파에 힘이 실리지 않음. 단기 상승 동력 약화 신호로 불타기(추가 매수) 자제. 추세 훼손(장대음봉+거래량 급증)은 아직 없음.\n\n## 엘리엇 파동\n\n상승 후반부(3파 후기~5파 진입 추정). 3/31 저점 806,865 → 6/8 저점 1,911,000 저점 절상. 청산은 파동이 아니라 가격(트레일링)으로만 결정.\n\n## RSI 다이버전스 — 없음\n\nRSI 59.2로 신고가에서도 과매수 아님. 모멘텀 소진 신호 없음(거래량 약화와는 다소 상충 → 중립).\n\n## 수급 / 신용\n\n- 공매도 거래대금 **시장 1위**(5,625억, 6/8) — 숏스퀴즈 연료이자 변동성 확대 요인.\n- 외국인 1Q26 추세 매도였으나 반등일 매수 동반(방향 전환 조짐). 기관 ETF 비중 확대.\n\n## 펀더멘털\n\n분기 영업이익 9.2 → 11.4 → 19.2 → **37.6조**, 1Q26 영업이익률 **72%**(엔비디아·TSMC 상회). forward PE **6.14배**로 성장률 대비 저평가. 순현금. 단, 마진 72%는 사이클 정점 신호이기도 함(양날의 검).\n\n## 포지션 전략\n\n- **추가 매수 금지**(거래량 약화 + 컨센 목표 근접 + 신고가).\n- 7월 하순 2Q26 실적 전 **1/3 익절**로 이익 확정.\n- 트레일링 스탑: 1차 손절선 1,911,000(6/8 스윙저점), 종가 MA20 이탈 시 청산. 신고가 갱신 시 손절선 상향(올리기만).\n- 빠질 때 물타기 금지.\n\n> SK하이닉스가 섹터 상대강도 1위. 삼성전자는 HBM4 반격·저밸류로 따라잡기 베팅 가치."
}